Workbook

Sheet Project Plan (2)
A1: PROJECT PLAN — MANAGEMENT & PERSONAL WORKSTREAMS
A3: Pillar / Scope | B3: Module / Section | C3: Feature / Sub-Tab / Item | D3: Frontend Effort (Days) | E3: Backend Effort (Days) | F3: Total Working Days
A4: PART 1: MANAGEMENT WORKSTREAM & ALL FEATURES
A5: Management | B5: Dashboard | C5: Admin Overview KPI Cards (Active Modules, Enrolled, Certifications, Completion Rate %) | D5: 1.5 | E5: 1 | F5: 2.5
A6: Management | B6: Dashboard | C6: Active Assignments Master Table (Search, Status Tabs, Department Filter) | D6: 2 | E6: 1 | F6: 3
A7: Management | B7: Dashboard | C7: Manager Team Dashboard (Direct Reports Roster, Team Completion %, Overdue Alerts) | D7: 2 | E7: 1.5 | F7: 3.5
A8: Management | B8: Dashboard | C8: One-Click 'Nudge / Remind' Action Button for Overdue Direct Reports | D8: 1 | E8: 0.5 | F8: 1.5
A9: Management | B9: Course Catalogue | C9: Upload Courses (SCORM 1.2 / 2004 ZIP Dropzone, Video, PDF, Manifest Auto-Inspector) | D9: 2.5 | E9: 2.5 | F9: 5
A10: Management | B10: Course Catalogue | C10: Course Management (One-Click Publish Toggle, Edit Metadata, Delete with File Cleanup) | D10: 1.5 | E10: 1 | F10: 2.5
A11: Management | B11: Course Catalogue | C11: Course Details & Syllabus Slide-Over Drawer (Admin View) | D11: 1.5 | E11: 0.5 | F11: 2
A12: Management | B12: Course Catalogue | C12: Course Enrolled Learners Roster Drawer (Filter by Status, Scores) | D12: 1.5 | E12: 1 | F12: 2.5
A13: Management | B13: Course Assignment | C13: Assign Course Modal (Individual, Department, Designation) | D13: 2 | E13: 1.5 | F13: 3.5
A14: Management | B14: Course Assignment | C14: Searchable Employee Multi-Select Picker (Live from Employee Central) | D14: 1.5 | E14: 1 | F14: 2.5
A15: Management | B15: Course Assignment | C15: Preset Due Dates Configuration (7d, 14d, 30d, Custom Date Picker) | D15: 1 | E15: 0.5 | F15: 1.5
A16: Management | B16: Course Assignment | C16: Mandatory Compliance vs Elective Flag & Notification Dispatch | D16: 1 | E16: 0.5 | F16: 1.5
... A30: Management | B30: Reports & Export | C30: One-Click Export to Excel (.xlsx) and CSV for Statutory Compliance Audits | D30: 1.5 | E30: 1.5 | F30: 3
A31: PART 2: PERSONAL WORKSTREAM & ALL FEATURES
A32: Personal | B32: Personal Dashboard | C32: Learner Dashboard Summary Cards (Enrolled, In Progress, Completed, Average Score) | D32: 1.5 | E32: 0.5 | F32: 2
A33: Personal | B33: Personal Dashboard | C33: 'Continue Learning' Smart Action Card (Instant resume from exact saved bookmark) | D33: 1.5 | E33: 0.5 | F33: 2
A34: Personal | B34: Personal Dashboard | C34: Learning Streak Flame Counter & Daily Milestone Tracker | D34: 1 | E34: 0.5 | F34: 1.5
A35: Personal | B35: Personal Dashboard | C35: Active Tasks Roster & Due Date Countdown Pills ('Due in 2 days', 'Overdue') | D35: 1.5 | E35: 0.5 | F35: 2
A36: Personal | B36: Personal Catalogue | C36: Browse Course Catalogue Grid (Live Search, Format Tabs, Department & Tag Filters) | D36: 2 | E36: 1 | F36: 3
A37: Personal | B37: Personal Catalogue | C37: Course Preview & Syllabus Details Slide-Over Drawer | D37: 1.5 | E37: 0.5 | F37: 2
A38: Personal | B38: Personal Catalogue | C38: Self-Enroll in Elective Courses Action Button | D38: 1 | E38: 0.5 | F38: 1.5
A39: Personal | B39: Course Player | C39: Universal SCORM 1.2 & 2004 Runtime Player (Dual window.API Bridge, CMI Auto-Sync) | D39: 2 | E39: 1.5 | F39: 3.5
A40: Personal | B40: Course Player | C40: Native Video Player (Speed 0.75x–2x, Resume Timestamp) & In-Browser PDF Reader | D40: 1.5 | E40: 0.5 | F40: 2
A41: Personal | B41: Course Player | C41: Player Top Bar (Course Breadcrumbs, Status Pill, Fullscreen Toggle, Exit Safeguard) | D41: 1 | E41: 0.5 | F41: 1.5
A42: Personal | B42: Course Player | C42: Collapsible Outline Sidebar & Completion Celebration Trigger | D42: 1.5 | E42: 0.5 | F42: 2
A43: Personal | B43: Personal Profile Tabs | C43: Employee Profile — 'Training & Learning' Dedicated Tab (/deploy/employees/:code) | D43: 1.5 | E43: 1 | F43: 2.5
... A60: — | B60: TOTAL WORKING DAYS | C60: Complete End-to-End Scope (Management + Personal) | D60: 71.5 | E60: 49.5 | F60: 121

Sheet Features
A1: LEARNING CENTRAL (FORGE) — PRACTICAL UI/UX & EMPLOYEE CENTRAL FEATURE MATRIX
A2: Actionable, screen-by-screen feature blueprint focusing on user flows, buttons, filters, catalog UI, and deep Employee Central (HRMS) integration.
A4: # | B4: Page / Screen | C4: UI Section / Component | D4: Feature Name | E4: Buttons, Filters & Controls | F4: Functional Flow & Logic | G4: Employee Central & Platform Integration | H4: Priority | I4: Status
A5: 1 | B5: Course Catalogue | C5: Top Filter & Search Bar | D5: Instant Live Search Input | E5: Search text input with clear 'X' button and magnifying glass icon | F5: As user types, course cards filter in real-time matching course title, description, or tags without full page reload. | G5: Matches course tags tied to Employee Central skill taxonomy. | H5: P1 | I5: Completed
A6: 2 | B6: Course Catalogue | C6: Top Filter & Search Bar | D6: Course Format Filter Tabs | E6: Pill buttons: 'All Formats', 'SCORM Package', 'Video', 'Document/PDF', 'External Link' | F6: Clicking a format tab instantly filters the catalog grid to show only matching delivery types. | G6: Allows employees to find quick micro-videos vs formal SCORM training. | H6: P1 | I6: Completed
A7: 3 | B7: Course Catalogue | C7: Top Filter & Search Bar | D7: Department Filter Dropdown | E7: Dropdown select populated dynamically with company departments (Tech, HR, Sales, Ops, Finance) | F7: Selecting a department shows courses tagged for or recommended to that specific business unit. | G7: Directly queries Employee Central 'departments' list from HRMS database. | H7: P1 | I7: In Progress
A8: 4 | B8: Course Catalogue | C8: Top Filter & Search Bar | D8: Difficulty Level Filter | E8: Dropdown select: 'All Levels', 'Beginner', 'Intermediate', 'Advanced' | F8: Filters the catalog grid by course difficulty level badge. | G8: Helps employees filter upskilling courses matching their current role tenure. | H8: P2 | I8: Completed
A9: 5 | B9: Course Catalogue | C9: Top Filter & Search Bar | D9: Estimated Duration Filter | E9: Dropdown / pill filter: '< 15 mins', '15-30 mins', '30-60 mins', '1+ hours' | F9: Filters courses by estimated completion time stored in duration_minutes. | G9: Enables quick micro-learning searches during work breaks. | H9: P2 | I9: Completed
A10: 6 | B10: Course Catalogue | C10: Top Filter & Search Bar | D10: Category & Skill Tag Chips | E10: Horizontal scrollable row of tag chips (e.g. 'Cybersecurity', 'POSH', 'React', 'Leadership') | F10: Clicking tag chip toggles multi-select filter; active tags highlight with purple pill styling. | G10: Tags map directly to Employee Central skills matrix. | H10: P2 | I10: Completed
A11: 7 | B11: Course Catalogue | C11: Top Filter & Search Bar | D11: Publish Status Filter (Admin View) | E11: Segmented toggle buttons: 'All', 'Published', 'Draft / Unpublished' | F11: Visible only to L&D Admins and HR Managers; lets administrators audit unpublished or draft courses. | G11: Restricted via forge.courses.manage permission gate. | H11: P1 | I11: Completed
A12: 8 | B12: Course Catalogue | C12: Catalog View Controls | D12: Grid vs List Layout Switcher | E12: Two toggle icons: 3x3 Grid Icon and List View Icon | F12: Switches catalog layout between visual card grid and a compact table view with sorting. | G12: Remembers user view preference in browser localStorage. | H12: P2 | I12: Planned
A13: 9 | B13: Course Catalogue | C13: Course Card Component | D13: Course Thumbnail & Format Badge | E13: Visual image container with fallback branded gradient + top-left Format Badge ('SCORM', 'VIDEO', 'DOC') | F13: Renders course thumbnail preview; shows clear visual badge of course delivery medium. | G13: Supports company brand asset library thumbnails. | H13: P1 | I13: Completed
A14: 10 | B14: Course Catalogue | C14: Course Card Component | D14: SCORM Edition Badge | E14: Purple pill badge: 'SCORM 1.2' or 'SCORM 2004' | F14: Displays automatically when course type is SCORM, indicating verified engine compatibility. | G14: Parsed automatically by ScormService during ZIP upload. | H14: P1 | I14: Completed
A15: 11 | B15: Course Catalogue | C15: Course Card Component | D15: Mandatory vs Elective Pill | E15: Red outline pill: 'Mandatory Compliance' / Blue outline pill: 'Elective Upskilling' | F15: Immediately alerts learners if course is a compulsory company-wide requirement. | G15: Tied to Employee Central compliance tracking rules. | H15: P1 | I15: In Progress
A16: 12 | B16: Course Catalogue | C16: Course Card Component | D16: Course Metadata Info Bar | E16: Clock icon with duration (e.g. '45m'), user icon with enrolled count (e.g. '128 enrolled') | F16: Shows quick glanceable metrics before user clicks to explore details. | G16: Live count of total enrollments in the tenant schema. | H16: P1 | I16: Completed
... A46: 42 | B46: Course Player | C46: Exit Protection | D46: Unsaved Progress Exit Warning Modal | E46: Confirmation dialog: 'Are you sure you want to exit? Your progress is being saved...' | F46: Safeguards against accidental tab closing before the final SCORM Commit network call completes. | G46: Ensures 100% data integrity for compliance audit records. | H46: P1 | I46: Completed
A47: 43 | B47: Course Management Studio | C47: Course Management Table | D47: Course Inventory Data Table | E47: Table listing all courses with Title, Type, Duration, Enrollments Count, Published Toggle, Actions | F47: Central admin dashboard for reviewing, filtering, and managing all learning assets. | G47: Shows total number of enrolled employees from Employee Central. | H47: P1 | I47: Completed
A48: 44 | B48: Course Management Studio | C48: Action Header | D48: Button: 'New Course / Upload' | E48: Primary action button: 'New Course' with upload icon | F48: Opens the CourseUploadModal for SCORM ZIP upload or manual course authoring. | G48: Gated by forge.courses.manage permission. | H48: P1 | I48: Completed
A49: 45 | B49: Course Management Studio | C49: Course Upload Modal | D49: Course Format Selector Tabs | E49: Radio cards / tabs: 'SCORM Package (.zip)', 'Video (MP4 / Stream)', 'Document (PDF)', 'External URL' | F49: Switching tab dynamically adjusts the modal inputs to match the chosen format. | G49: Ensures clean metadata collection tailored to each content type. | H49: P1 | I49: Completed
A50: 46 | B50: Course Management Studio | C50: Course Upload Modal | D50: SCORM Drag-and-Drop Dropzone | E50: Dashed border dropzone accepting .zip archives with file picker browse button | F50: User drags any SCORM zip; displays file name and size with clear visual feedback. | G50: Validates file extension before uploading to backend. | H50: P1 | I50: Completed
A51: 47 | B51: Course Management Studio | C51: Course Upload Modal | D51: Live Upload Progress Bar | E51: Animated progress bar showing upload % and transfer speed | F51: Provides real-time feedback during large SCORM package uploads (up to 200MB). | G51: Prevents user from clicking submit multiple times. | H51: P1 | I51: Completed
A52: 48 | B52: Course Management Studio | C52: Course Upload Modal | D52: Auto-Inspected Manifest Preview Card | E52: Card previewing parsed Title, Detected SCORM Version ('1.2' / '2004'), and Launch File ('index.html') | F52: Automatically populated immediately after ZIP upload by backend ScormService. | G52: Verifies manifest validity before course is saved to the database. | H52: P1 | I52: Completed
A53: 49 | B53: Course Management Studio | C53: Course Upload Modal | D53: Course Metadata Form Fields | E53: Inputs: Title, Description (textarea), Estimated Duration (minutes), Difficulty dropdown | F53: Allows admin to override or enrich the automatically extracted manifest metadata. | G53: Saves directly to forge_courses table. | H53: P1 | I53: Completed
A54: 50 | B54: Course Management Studio | C54: Course Upload Modal | D54: Target Department & Designation Multi-Select | E54: Searchable multi-select dropdowns populated with Employee Central departments and job titles | F54: Tags course for specific departments (e.g. Sales, Engineering) for catalog filtering. | G54: Directly queries Employee Central master lists. | H54: P1 | I54: In Progress
A55: 51 | B55: Course Management Studio | C55: Course Upload Modal | D55: Target Skill Tags Input | E55: Chip input: type skill name and hit Enter (e.g. 'Customer Service', 'Python', 'ISO-27001') | F55: Maps course completion to specific skill tags that sync to employee profiles. | G55: Connects Forge courses directly to Employee Central skills matrix. | H55: P1 | I55: Completed
A56: 52 | B56: Course Management Studio | C56: Course Upload Modal | D56: Thumbnail Image Dropzone / URL | E56: Image dropzone for course cover banner (PNG/JPG) or custom URL input | F56: Provides visual branding for the course card in the catalog and learner portal. | G56: Auto-generates high-res and mobile-optimized thumbnails. | H56: P2 | I56: Completed
A57: 53 | B57: Course Management Studio | C57: Course Upload Modal | D57: Toggle: 'Publish Immediately' | E57: Switch toggle: 'Publish Immediately' (active = visible in catalog, inactive = saved as draft) | F57: Lets admins stage courses as drafts for review before making them visible to employees. | G57: Sets is_published boolean in forge_courses table. | H57: P1 | I57: Completed
A58: 54 | B58: Course Management Studio | C58: Course Upload Modal | D58: Action Buttons: 'Save Course' & 'Cancel' | E58: Secondary 'Cancel' button and primary 'Create Course' button with spinner state | F58: Submits multipart form to /api/forge/courses/upload-scorm and refreshes catalog table on success. | G58: Triggers success toast notification upon successful creation. | H58: P1 | I58: Completed
... A119: 115 | B119: Reports & Export Center | C119: Export Action Buttons | D119: Export Buttons: 'Export Excel (.xlsx)' & 'Export CSV' | E119: Buttons with Excel and CSV icons: downloads filtered dataset immediately as styled spreadsheet | F119: Generates clean file with employee code, name, department, course, score, and completion timestamp. | G119: Instant one-click audit submission for statutory regulatory reviews. | H119: P1 | I119: In Progress

Sheet Summary
A1: LEARNING CENTRAL (FORGE) — PAGE & MODULE SUMMARY
A2: Roll-up metrics calculated dynamically from the Features sheet. Updates automatically when Priority or Status changes.
A4: Page / Module | B4: Total Features | C4: P1 (Must-Have) | D4: P2 (High-Value) | E4: P3 (Enhancement) | F4: Completed | G4: % Completed
A5: Course Catalogue | B5: =COUNTIF(Features!$B$5:$B$119, A5) -> 18 | C5: =COUNTIFS(Features!$B$5:$B$119, $A5, Features!$H$5:$H$119, "P1") -> 12 | D5: =COUNTIFS(Features!$B$5:$B$119, $A5, Features!$H$5:$H$119, "P2") -> 6 | E5: =COUNTIFS(Features!$B$5:$B$119, $A5, Features!$H$5:$H$119, "P3") -> 0 | F5: =COUNTIFS(Features!$B$5:$B$119, $A5, Features!$I$5:$I$119, "Completed") -> 13 | G5: =IF(B5=0, 0, F5/B5) -> 0.72222222
A6: My Learning Portal | B6: =COUNTIF(Features!$B$5:$B$119, A6) -> 12 | C6: =COUNTIFS(Features!$B$5:$B$119, $A6, Features!$H$5:$H$119, "P1") -> 10 | D6: =COUNTIFS(Features!$B$5:$B$119, $A6, Features!$H$5:$H$119, "P2") -> 2 | E6: =COUNTIFS(Features!$B$5:$B$119, $A6, Features!$H$5:$H$119, "P3") -> 0 | F6: =COUNTIFS(Features!$B$5:$B$119, $A6, Features!$I$5:$I$119, "Completed") -> 11 | G6: =IF(B6=0, 0, F6/B6) -> 0.91666667
A7: Course Player | B7: =COUNTIF(Features!$B$5:$B$119, A7) -> 12 | C7: =COUNTIFS(Features!$B$5:$B$119, $A7, Features!$H$5:$H$119, "P1") -> 10 | D7: =COUNTIFS(Features!$B$5:$B$119, $A7, Features!$H$5:$H$119, "P2") -> 2 | E7: =COUNTIFS(Features!$B$5:$B$119, $A7, Features!$H$5:$H$119, "P3") -> 0 | F7: =COUNTIFS(Features!$B$5:$B$119, $A7, Features!$I$5:$I$119, "Completed") -> 8 | G7: =IF(B7=0, 0, F7/B7) -> 0.66666667
A8: Course Management Studio | B8: =COUNTIF(Features!$B$5:$B$119, A8) -> 17 | C8: =COUNTIFS(Features!$B$5:$B$119, $A8, Features!$H$5:$H$119, "P1") -> 16 | D8: =COUNTIFS(Features!$B$5:$B$119, $A8, Features!$H$5:$H$119, "P2") -> 1 | E8: =COUNTIFS(Features!$B$5:$B$119, $A8, Features!$H$5:$H$119, "P3") -> 0 | F8: =COUNTIFS(Features!$B$5:$B$119, $A8, Features!$I$5:$I$119, "Completed") -> 16 | G8: =IF(B8=0, 0, F8/B8) -> 0.94117647
A9: Assign Training Modal | B9: =COUNTIF(Features!$B$5:$B$119, A9) -> 11 | C9: =COUNTIFS(Features!$B$5:$B$119, $A9, Features!$H$5:$H$119, "P1") -> 11 | D9: =COUNTIFS(Features!$B$5:$B$119, $A9, Features!$H$5:$H$119, "P2") -> 0 | E9: =COUNTIFS(Features!$B$5:$B$119, $A9, Features!$H$5:$H$119, "P3") -> 0 | F9: =COUNTIFS(Features!$B$5:$B$119, $A9, Features!$I$5:$I$119, "Completed") -> 6 | G9: =IF(B9=0, 0, F9/B9) -> 0.54545455
A10: Employee Central Integration | B10: =COUNTIF(Features!$B$5:$B$119, A10) -> 10 | C10: =COUNTIFS(Features!$B$5:$B$119, $A10, Features!$H$5:$H$119, "P1") -> 5 | D10: =COUNTIFS(Features!$B$5:$B$119, $A10, Features!$H$5:$H$119, "P2") -> 5 | E10: =COUNTIFS(Features!$B$5:$B$119, $A10, Features!$H$5:$H$119, "P3") -> 0 | F10: =COUNTIFS(Features!$B$5:$B$119, $A10, Features!$I$5:$I$119, "Completed") -> 0 | G10: =IF(B10=0, 0, F10/B10) -> 0
A11: Manager Team Dashboard | B11: =COUNTIF(Features!$B$5:$B$119, A11) -> 7 | C11: =COUNTIFS(Features!$B$5:$B$119, $A11, Features!$H$5:$H$119, "P1") -> 5 | D11: =COUNTIFS(Features!$B$5:$B$119, $A11, Features!$H$5:$H$119, "P2") -> 2 | E11: =COUNTIFS(Features!$B$5:$B$119, $A11, Features!$H$5:$H$119, "P3") -> 0 | F11: =COUNTIFS(Features!$B$5:$B$119, $A11, Features!$I$5:$I$119, "Completed") -> 0 | G11: =IF(B11=0, 0, F11/B11) -> 0
A12: Forge Dashboard Overview | B12: =COUNTIF(Features!$B$5:$B$119, A12) -> 11 | C12: =COUNTIFS(Features!$B$5:$B$119, $A12, Features!$H$5:$H$119, "P1") -> 10 | D12: =COUNTIFS(Features!$B$5:$B$119, $A12, Features!$H$5:$H$119, "P2") -> 1 | E12: =COUNTIFS(Features!$B$5:$B$119, $A12, Features!$H$5:$H$119, "P3") -> 0 | F12: =COUNTIFS(Features!$B$5:$B$119, $A12, Features!$I$5:$I$119, "Completed") -> 9 | G12: =IF(B12=0, 0, F12/B12) -> 0.81818182
A13: Assessment & Quiz Hub | B13: =COUNTIF(Features!$B$5:$B$119, A13) -> 8 | C13: =COUNTIFS(Features!$B$5:$B$119, $A13, Features!$H$5:$H$119, "P1") -> 6 | D13: =COUNTIFS(Features!$B$5:$B$119, $A13, Features!$H$5:$H$119, "P2") -> 2 | E13: =COUNTIFS(Features!$B$5:$B$119, $A13, Features!$H$5:$H$119, "P3") -> 0 | F13: =COUNTIFS(Features!$B$5:$B$119, $A13, Features!$I$5:$I$119, "Completed") -> 0 | G13: =IF(B13=0, 0, F13/B13) -> 0
A14: Certificates & Verification | B14: =COUNTIF(Features!$B$5:$B$119, A14) -> 5 | C14: =COUNTIFS(Features!$B$5:$B$119, $A14, Features!$H$5:$H$119, "P1") -> 4 | D14: =COUNTIFS(Features!$B$5:$B$119, $A14, Features!$H$5:$H$119, "P2") -> 1 | E14: =COUNTIFS(Features!$B$5:$B$119, $A14, Features!$H$5:$H$119, "P3") -> 0 | F14: =COUNTIFS(Features!$B$5:$B$119, $A14, Features!$I$5:$I$119, "Completed") -> 0 | G14: =IF(B14=0, 0, F14/B14) -> 0
A15: Reports & Export Center | B15: =COUNTIF(Features!$B$5:$B$119, A15) -> 4 | C15: =COUNTIFS(Features!$B$5:$B$119, $A15, Features!$H$5:$H$119, "P1") -> 4 | D15: =COUNTIFS(Features!$B$5:$B$119, $A15, Features!$H$5:$H$119, "P2") -> 0 | E15: =COUNTIFS(Features!$B$5:$B$119, $A15, Features!$H$5:$H$119, "P3") -> 0 | F15: =COUNTIFS(Features!$B$5:$B$119, $A15, Features!$I$5:$I$119, "Completed") -> 0 | G15: =IF(B15=0, 0, F15/B15) -> 0
A16: TOTAL ALL MODULES | B16: =SUM(B5:B15) -> 115 | C16: =SUM(C5:C15) -> 93 | D16: =SUM(D5:D15) -> 22 | E16: =SUM(E5:E15) -> 0 | F16: =SUM(F5:F15) -> 63 | G16: =IF(B16=0,0,F16/B16) -> 0.54782609

Sheet Employee Central Integration
A1: EMPLOYEE CENTRAL (HRMS) & LEARNING CENTRAL INTEGRATION MAP
A2: Technical data flow and touchpoints connecting Employee Central (Deploy) with Learning Central (Forge).
A4: HRMS Touchpoint / Screen | B4: Employee Central Data Entity | C4: Learning Central (Forge) Action | D4: Business Value & User Flow
A5: Employee Profile (/deploy/employees/:code) | B5: employees table (employee_code, name, department, designation, email, manager_id) | C5: Renders new 'Training & Certifications' tab listing active, completed, and overdue courses with progress % and certificate download links. | D5: HR and managers can inspect an employee's continuous learning history directly alongside attendance and salary records.
A6: New Hire Onboarding Pipeline | B6: Employee creation event (POST /api/employees) | C6: Automated rule assigns mandatory compliance curriculum (POSH, InfoSec, Workplace Safety) with 14-day due date. | D6: Zero-touch onboarding: new hires log in on Day 1 to find their mandatory onboarding training ready.
A7: Manager Team View (/deploy/team) | B7: reporting_manager_id relationship in employees table | C7: Filters direct reports and renders team compliance cards, overdue alerts, and one-click 'Nudge' reminder buttons. | D7: Empowers team leads and managers to enforce 100% compliance without having to ask HR for manual spreadsheets.
A8: Department & Role Catalog Filtering | B8: departments and designations master tables in Employee Central | C8: Populates dropdown filters in Course Catalogue and Assign Training modal directly from live HRMS organizational structure. | D8: Ensures course assignments always target active departments and real job roles without duplicate data entry.
A9: Skills Matrix & Competency Profile | B9: employee_skills table (employee_code, skill_id, proficiency_level, verified_badge) | C9: When an employee completes a course with passing score, linked skill tags automatically update to verified status in employee profile. | D9: Eliminates manual skill updating and provides real-time talent capability data for project staffing.
A10: Annual Performance Review (Appraisals) | B10: performance_reviews table in Deploy module | C10: Embeds total training hours, courses completed, and average assessment scores during the appraisal cycle. | D10: Allows managers to quantitatively factor employee learning dedication and upskilling into annual merit raises.
A11: Employee Resignation & Exit Clearance | B11: employee_exit_clearance table in Deploy module | C11: Adds mandatory checklist item verifying all statutory compliance courses were completed prior to generating relieving letter. | D11: Guarantees corporate legal defensibility in case of future regulatory or labor disputes.
A12: Employee Document Vault | B12: employee_documents table in Deploy module | C12: Automatically archives a copy of every earned certificate PDF directly into the employee's HR document repository. | D12: Centralizes all employee credentials in one compliant, searchable archive.
